[{"buildOrder":500,"reportUrl":"https://TheFocusTech.github.io/DomainQA/500/","reportName":"Allure Report with history","data":{"run":8,"retry":2}},{"buildOrder":499,"reportUrl":"https://TheFocusTech.github.io/DomainQA/499/","reportName":"Allure Report with history","data":{"run":157,"retry":193}},{"buildOrder":498,"reportUrl":"https://TheFocusTech.github.io/DomainQA/498/","reportName":"Allure Report with history","data":{"run":7,"retry":0}},{"buildOrder":497,"reportUrl":"https://TheFocusTech.github.io/DomainQA/497/","reportName":"Allure Report with history","data":{"run":194,"retry":57}},{"buildOrder":496,"reportUrl":"https://TheFocusTech.github.io/DomainQA/496/","reportName":"Allure Report with history","data":{"run":314,"retry":310}},{"buildOrder":495,"reportUrl":"https://TheFocusTech.github.io/DomainQA/495/","reportName":"Allure Report with history","data":{"run":39,"retry":0}},{"buildOrder":494,"reportUrl":"https://TheFocusTech.github.io/DomainQA/494/","reportName":"Allure Report with history","data":{"run":157,"retry":3}},{"buildOrder":493,"reportUrl":"https://TheFocusTech.github.io/DomainQA/493/","reportName":"Allure Report with history","data":{"run":67,"retry":1}},{"buildOrder":492,"reportUrl":"https://TheFocusTech.github.io/DomainQA/492/","reportName":"Allure Report with history","data":{"run":157,"retry":2}},{"buildOrder":491,"reportUrl":"https://TheFocusTech.github.io/DomainQA/491/","reportName":"Allure Report with history","data":{"run":157,"retry":2}},{"buildOrder":490,"reportUrl":"https://TheFocusTech.github.io/DomainQA/490/","reportName":"Allure Report with history","data":{"run":131,"retry":0}},{"buildOrder":489,"reportUrl":"https://TheFocusTech.github.io/DomainQA/489/","reportName":"Allure Report with history","data":{"run":131,"retry":1}},{"buildOrder":488,"reportUrl":"https://TheFocusTech.github.io/DomainQA/488/","reportName":"Allure Report with history","data":{"run":130,"retry":3}},{"buildOrder":487,"reportUrl":"https://TheFocusTech.github.io/DomainQA/487/","reportName":"Allure Report with history","data":{"run":131,"retry":1}},{"buildOrder":487,"reportUrl":"https://TheFocusTech.github.io/DomainQA/487/","reportName":"Allure Report with history","data":{"run":131,"retry":5}},{"buildOrder":482,"reportUrl":"https://TheFocusTech.github.io/DomainQA/482/","reportName":"Allure Report with history","data":{"run":131,"retry":5}},{"buildOrder":486,"reportUrl":"https://TheFocusTech.github.io/DomainQA/486/","reportName":"Allure Report with history","data":{"run":156,"retry":1}},{"buildOrder":485,"reportUrl":"https://TheFocusTech.github.io/DomainQA/485/","reportName":"Allure Report with history","data":{"run":131,"retry":0}},{"buildOrder":484,"reportUrl":"https://TheFocusTech.github.io/DomainQA/484/","reportName":"Allure Report with history","data":{"run":130,"retry":1}},{"buildOrder":483,"reportUrl":"https://TheFocusTech.github.io/DomainQA/483/","reportName":"Allure Report with history","data":{"run":130,"retry":3}}]